neural_net/nueral.py
ReLU_nueral_network-1.0.0.dist-info/LICENSE
ReLU_nueral_network-1.0.0.dist-info/METADATA
ReLU_nueral_network-1.0.0.dist-info/WHEEL
ReLU_nueral_network-1.0.0.dist-info/entry_points.txt
ReLU_nueral_network-1.0.0.dist-info/top_level.txt
ReLU_nueral_network-1.0.0.dist-info/RECORD
