Metadata-Version: 2.1
Name: ReLU-nueral-network
Version: 1.0.0
Summary: A Python package for direct implementation of ReLU network.
Home-page: https://github.com/yadav-vikas/ReLU_network
Author: Vikas Yadav
Author-email: yadavvikas859@gmail.com
License: MIT
Platform: UNKNOWN
Classifier: License :: OSI Approved :: MIT License
Classifier: Programming Language :: Python :: 3
Classifier: Programming Language :: Python :: 3.7
Requires-Dist: numpy
Requires-Dist: sklearn
